README.rst
setup.cfg
setup.py
QRC/AES.py
QRC/Client.py
QRC/Common.py
QRC/KeyRing.py
QRC/Server.py
QRC/__init__.py
QRC.egg-info/PKG-INFO
QRC.egg-info/SOURCES.txt
QRC.egg-info/dependency_links.txt
QRC.egg-info/requires.txt
QRC.egg-info/top_level.txt