Metadata-Version: 1.1
Name: QRC
Version: 0.0.2
Summary: Quantum resistant cryptography suite with socket support
Home-page: https://github.com/Ohge/QRC
Author: Christopher Ohge
Author-email: chris.ohge@gmail.com
License: MIT
Keywords: quantum resistant elliptic curve ecc aes crypto cipher encrypt decrypt socket
Platform: UNKNOWN
Classifier: Development Status :: 3 - Alpha
Classifier: Intended Audience :: Developers
Classifier: License :: OSI Approved :: MIT License
Classifier: Topic :: Software Development :: Libraries :: Python Modules
Classifier: Topic :: Communications
Classifier: Topic :: Security :: Cryptography
Classifier: Topic :: Internet
Classifier: Programming Language :: Python :: 2.7
